ubika_waap_api_client/__init__.py
ubika_waap_api_client/api_client.py
ubika_waap_api_client/configuration.py
ubika_waap_api_client/exceptions.py
ubika_waap_api_client/rest.py
ubika_waap_api_client/api/__init__.py
ubika_waap_api_client/api/default_api.py
ubika_waap_api_client/models/__init__.py
ubika_waap_api_client/models/add_network_interface.py
ubika_waap_api_client/models/add_network_interface_success.py
ubika_waap_api_client/models/add_network_interface_success_data.py
ubika_waap_api_client/models/add_network_interface_used_by_success_array.py
ubika_waap_api_client/models/add_reverse_proxy.py
ubika_waap_api_client/models/add_reverse_proxy_block_default_tunnel.py
ubika_waap_api_client/models/add_reverse_proxy_labels_array.py
ubika_waap_api_client/models/add_reverse_proxy_labels_success_array.py
ubika_waap_api_client/models/add_reverse_proxy_logs.py
ubika_waap_api_client/models/add_reverse_proxy_monitor.py
ubika_waap_api_client/models/add_reverse_proxy_no_log_on.py
ubika_waap_api_client/models/add_reverse_proxy_profile.py
ubika_waap_api_client/models/add_reverse_proxy_profile_success.py
ubika_waap_api_client/models/add_reverse_proxy_profile_success_data.py
ubika_waap_api_client/models/add_reverse_proxy_success.py
ubika_waap_api_client/models/add_reverse_proxy_success_data.py
ubika_waap_api_client/models/add_reverse_proxy_success_data_logs.py
ubika_waap_api_client/models/add_reverse_proxy_syslog_destinations.py
ubika_waap_api_client/models/addsslprofiles.py
ubika_waap_api_client/models/addsslprofiles_success.py
ubika_waap_api_client/models/addsslprofiles_success_data.py
ubika_waap_api_client/models/apply.py
ubika_waap_api_client/models/apply_appliances_array.py
ubika_waap_api_client/models/apply_network_devices_array.py
ubika_waap_api_client/models/apply_reverse_proxies_array.py
ubika_waap_api_client/models/apply_secondary_tunnels_array.py
ubika_waap_api_client/models/apply_ssl_key_uid.py
ubika_waap_api_client/models/apply_success.py
ubika_waap_api_client-1.0.1.dist-info/METADATA
ubika_waap_api_client-1.0.1.dist-info/WHEEL
ubika_waap_api_client-1.0.1.dist-info/top_level.txt
ubika_waap_api_client-1.0.1.dist-info/RECORD
