Metadata-Version: 2.1
Name: ubika-waap-api-client
Version: 1.0.1
Summary: UBIKA WAAP client API to automate WAAP administration tasks
Home-page: 
Author: OpenAPI Generator community
Author-email: UBIKA <info@ubikasec.com>
Project-URL: homepage, https://www.ubikasec.com
Project-URL: support, https://my.ubikasec.com
Keywords: UBIKA WAAP,Application,API,Security
Classifier: Development Status :: 5 - Production/Stable
Classifier: Intended Audience :: Developers
Classifier: License :: OSI Approved :: MIT License
Classifier: Natural Language :: English
Classifier: Operating System :: OS Independent
Classifier: Programming Language :: Python :: 3.7
Classifier: Topic :: Software Development :: Libraries :: Python Modules
Requires-Python: >=3.4
Requires-Dist: certifi (>=14.05.14)
Requires-Dist: six (>=1.10)
Requires-Dist: python-dateutil (>=2.5.3)
Requires-Dist: setuptools (>=21.0.0)
Requires-Dist: urllib3 (>=1.15.1)
Requires-Dist: future ; python_version <= "2.7"
